elections/__init__.py
elections/constants.py
elections/data/parties.pkl
elections/data/years.pkl
elections/data/2018/ak-executive-seats.pkl
elections/data/2018/ak-judicial-seats.pkl
elections/data/2018/ak-legislative-seats.pkl
elections/data/2018/al-executive-seats.pkl
elections/data/2018/al-judicial-seats.pkl
elections/data/2018/al-legislative-seats.pkl
elections/data/2018/ar-executive-seats.pkl
elections/data/2018/ar-judicial-seats.pkl
elections/data/2018/ar-legislative-seats.pkl
elections/data/2018/az-executive-seats.pkl
elections/data/2018/az-judicial-seats.pkl
elections/data/2018/az-legislative-seats.pkl
elections/data/2018/ca-executive-seats.pkl
elections/data/2018/ca-judicial-seats.pkl
elections/data/2018/ca-legislative-seats.pkl
elections/data/2018/co-executive-seats.pkl
elections/data/2018/co-judicial-seats.pkl
elections/data/2018/co-legislative-seats.pkl
elections/data/2018/ct-executive-seats.pkl
elections/data/2018/ct-judicial-seats.pkl
elections/data/2018/ct-legislative-seats.pkl
elections/data/2018/de-executive-seats.pkl
elections/data/2018/de-judicial-seats.pkl
elections/data/2018/de-legislative-seats.pkl
elections/data/2018/elections.pkl
elections/data/2018/electoral-votes.pkl
elections/data/2018/federal-executive-seats.pkl
elections/data/2018/federal-legislative-seats.pkl
elections/data/2018/fl-executive-seats.pkl
elections/data/2018/fl-judicial-seats.pkl
elections/data/2018/fl-legislative-seats.pkl
elections/data/2018/ga-executive-seats.pkl
elections/data/2018/ga-judicial-seats.pkl
elections/data/2018/ga-legislative-seats.pkl
elections/data/2018/hi-executive-seats.pkl
elections/data/2018/hi-judicial-seats.pkl
elections/data/2018/hi-legislative-seats.pkl
elections/data/2018/ia-executive-seats.pkl
elections/data/2018/ia-judicial-seats.pkl
elections/data/2018/ia-legislative-seats.pkl
elections/data/2018/id-executive-seats.pkl
elections/data/2018/id-judicial-seats.pkl
elections/data/2018/id-legislative-seats.pkl
us_elections-0.7.2.dist-info/LICENSE
us_elections-0.7.2.dist-info/METADATA
us_elections-0.7.2.dist-info/WHEEL
us_elections-0.7.2.dist-info/top_level.txt
us_elections-0.7.2.dist-info/RECORD
