Metadata-Version: 2.1
Name: us-elections
Version: 0.7.2
Summary: U.S. election and government metadata
Home-page: https://github.com/The-Politico/us-elections/
Author: POLITICO Interactive News
Author-email: interactives@politico.com
License: MIT
Download-URL: https://github.com/The-Politico/us-elections/archive/0.7.2.tar.gz
Platform: any
Classifier: License :: OSI Approved :: MIT License
Classifier: Operating System :: OS Independent
Classifier: Programming Language :: Python :: 3.4
Classifier: Programming Language :: Python :: 3.5
Classifier: Programming Language :: Python :: 3.6
Classifier: Programming Language :: Python :: 3.7
Classifier: Topic :: Internet :: WWW/HTTP
Requires-Dist: us (<2,>=1)
Provides-Extra: test
Requires-Dist: pytest ; extra == 'test'
